odyn/__init__.py
odyn/_client.py
odyn/_exceptions.py
odyn/py.typed
odyn/sessions.py
odyn-1.0.4.dist-info/METADATA
odyn-1.0.4.dist-info/WHEEL
odyn-1.0.4.dist-info/entry_points.txt
odyn-1.0.4.dist-info/RECORD
