Metadata-Version: 2.4
Name: odyn
Version: 1.0.4
Summary: Odyn – Python adapter for Microsoft Dynamics 365 Business Central OData v4 API
Project-URL: Homepage, https://github.com/konspec/odyn
Project-URL: Documentation, https://konspec.github.io/odyn/
Project-URL: Repository, https://github.com/konspec/odyn
Author-email: kon-fin <erpsupport@konspec.com>
Requires-Python: >=3.12
Requires-Dist: loguru>=0.7.3
Requires-Dist: requests>=2.32.4
